[{"c_country": "US", "visits": 29166}, {"c_country": "FR", "visits": 12445}, {"c_country": "HK", "visits": 10461}, {"c_country": "CN", "visits": 3751}, {"c_country": "CA", "visits": 3526}, {"c_country": "SG", "visits": 2921}, {"c_country": "JP", "visits": 2398}, {"c_country": "IE", "visits": 1597}, {"c_country": "IT", "visits": 1409}, {"c_country": "DE", "visits": 1303}, {"c_country": "KR", "visits": 1116}, {"c_country": "GB", "visits": 835}, {"c_country": "EC", "visits": 775}, {"c_country": "IN", "visits": 730}, {"c_country": "NL", "visits": 586}, {"c_country": "BR", "visits": 547}, {"c_country": "PL", "visits": 401}, {"c_country": "IR", "visits": 357}, {"c_country": "SE", "visits": 336}, {"c_country": "BG", "visits": 334}, {"c_country": "CH", "visits": 307}, {"c_country": "ES", "visits": 263}, {"c_country": "AT", "visits": 263}, {"c_country": "NO", "visits": 257}, {"c_country": "VN", "visits": 254}, {"c_country": "FI", "visits": 220}, {"c_country": "AU", "visits": 216}, {"c_country": "MX", "visits": 169}, {"c_country": "RU", "visits": 142}, {"c_country": "HU", "visits": 132}, {"c_country": "ID", "visits": 123}, {"c_country": "SC", "visits": 109}, {"c_country": "TR", "visits": 89}, {"c_country": "AR", "visits": 72}, {"c_country": "PK", "visits": 64}, {"c_country": "IQ", "visits": 59}, {"c_country": "TW", "visits": 58}, {"c_country": "BD", "visits": 57}, {"c_country": "RO", "visits": 45}, {"c_country": "SA", "visits": 45}, {"c_country": "BE", "visits": 44}, {"c_country": "PH", "visits": 41}, {"c_country": "PT", "visits": 38}, {"c_country": "EG", "visits": 38}, {"c_country": "DZ", "visits": 35}, {"c_country": "VE", "visits": 30}, {"c_country": "NZ", "visits": 29}, {"c_country": "AE", "visits": 29}, {"c_country": "TH", "visits": 29}, {"c_country": "CO", "visits": 26}, {"c_country": "UY", "visits": 26}, {"c_country": "UA", "visits": 26}, {"c_country": "MY", "visits": 25}, {"c_country": "LT", "visits": 25}, {"c_country": "IL", "visits": 23}, {"c_country": "HR", "visits": 23}, {"c_country": "DK", "visits": 23}, {"c_country": "ZA", "visits": 22}, {"c_country": "MA", "visits": 22}, {"c_country": "UZ", "visits": 22}, {"c_country": "CZ", "visits": 19}, {"c_country": "KE", "visits": 18}, {"c_country": "GR", "visits": 18}, {"c_country": "CL", "visits": 17}, {"c_country": "BO", "visits": 16}, {"c_country": "PE", "visits": 16}, {"c_country": "AM", "visits": 15}, {"c_country": "PS", "visits": 15}, {"c_country": "MG", "visits": 14}, {"c_country": "JO", "visits": 14}, {"c_country": "NP", "visits": 14}, {"c_country": "OM", "visits": 12}, {"c_country": "TN", "visits": 9}, {"c_country": "RS", "visits": 9}, {"c_country": "KZ", "visits": 7}, {"c_country": "PY", "visits": 7}, {"c_country": "JM", "visits": 7}, {"c_country": "BZ", "visits": 7}, {"c_country": "NG", "visits": 6}, {"c_country": "BA", "visits": 6}, {"c_country": "CR", "visits": 5}, {"c_country": "ET", "visits": 5}, {"c_country": "IS", "visits": 5}, {"c_country": "EE", "visits": 4}, {"c_country": "SN", "visits": 4}, {"c_country": "GT", "visits": 4}, {"c_country": "GE", "visits": 4}, {"c_country": "KH", "visits": 4}, {"c_country": "GD", "visits": 3}, {"c_country": "SY", "visits": 3}, {"c_country": "VG", "visits": 3}, {"c_country": "LV", "visits": 3}, {"c_country": "LB", "visits": 3}, {"c_country": "LK", "visits": 3}, {"c_country": "AZ", "visits": 3}, {"c_country": "SD", "visits": 3}, {"c_country": "KG", "visits": 3}, {"c_country": "GA", "visits": 3}, {"c_country": "BH", "visits": 3}, {"c_country": "DO", "visits": 2}, {"c_country": "BS", "visits": 2}, {"c_country": "MD", "visits": 2}, {"c_country": "CG", "visits": 2}, {"c_country": "MM", "visits": 2}, {"c_country": "NI", "visits": 2}, {"c_country": "AL", "visits": 2}, {"c_country": "UG", "visits": 2}, {"c_country": "XK", "visits": 2}, {"c_country": "LY", "visits": 2}, {"c_country": "MN", "visits": 2}, {"c_country": "BY", "visits": 2}, {"c_country": "LU", "visits": 1}, {"c_country": "TJ", "visits": 1}, {"c_country": "PA", "visits": 1}, {"c_country": "SK", "visits": 1}, {"c_country": "MU", "visits": 1}, {"c_country": "HN", "visits": 1}, {"c_country": "SI", "visits": 1}, {"c_country": "GH", "visits": 1}, {"c_country": "QA", "visits": 1}, {"c_country": "KW", "visits": 1}, {"c_country": "CM", "visits": 1}, {"c_country": "MT", "visits": 1}, {"c_country": "ML", "visits": 1}, {"c_country": "AO", "visits": 1}, {"c_country": "CD", "visits": 1}, {"c_country": "KI", "visits": 1}, {"c_country": "CI", "visits": 1}]